confluent_kafka/__init__.py
confluent_kafka/cimpl.cpython-39-darwin.so
confluent_kafka/deserializing_consumer.py
confluent_kafka/error.py
confluent_kafka/serializing_producer.py
confluent_kafka/admin/__init__.py
confluent_kafka/avro/__init__.py
confluent_kafka/avro/cached_schema_registry_client.py
confluent_kafka/avro/error.py
confluent_kafka/avro/load.py
confluent_kafka/avro/serializer/__init__.py
confluent_kafka/avro/serializer/message_serializer.py
confluent_kafka/kafkatest/__init__.py
confluent_kafka/kafkatest/verifiable_client.py
confluent_kafka/kafkatest/verifiable_consumer.py
confluent_kafka/kafkatest/verifiable_producer.py
confluent_kafka/schema_registry/__init__.py
confluent_kafka/schema_registry/avro.py
confluent_kafka/schema_registry/error.py
confluent_kafka/schema_registry/json_schema.py
confluent_kafka/schema_registry/protobuf.py
confluent_kafka/schema_registry/schema_registry_client.py
confluent_kafka/serialization/__init__.py
pup_confluent_kafka-1.7.1.data/data/LICENSE.txt
pup_confluent_kafka-1.7.1.dist-info/LICENSE.txt
pup_confluent_kafka-1.7.1.dist-info/METADATA
pup_confluent_kafka-1.7.1.dist-info/WHEEL
pup_confluent_kafka-1.7.1.dist-info/top_level.txt
pup_confluent_kafka-1.7.1.dist-info/RECORD
